{
  "Biologi-Stella-kapitel-1/002": {
    "ocr": {
      "psm7": "",
      "psm6": "information.\nsi fu | -"
    },
    "chapter": null,
    "page_num": null
  },
  "Biologi-Stella-kapitel-1/001": {
    "ocr": {
      "psm7": "4 ; 4 - (ESS For ottan)",
      "psm6": "toreatry |\n13 EC FSC\" C118234"
    },
    "chapter": "13 EC FSC\" C118",
    "page_num": 234
  },
  "Biologi-Stella-kapitel-1/004": {
    "ocr": {
      "psm7": "",
      "psm6": ""
    },
    "chapter": null,
    "page_num": null
  },
  "Biologi-Stella-kapitel-1/003": {
    "ocr": {
      "psm7": "",
      "psm6": "N D\nLE Å \"| md\na KE IFS\n0 LR I\nNä = > - på = 4\nJm KR 2 SA i STR\nJK far Ala IE fy RR\nSe AS ) SST - 5\n| ; 4 AL 0 saa\n\"7 ERE"
    },
    "chapter": "Se AS ) SST -",
    "page_num": 5
  },
  "Biologi-Stella-kapitel-1/005": {
    "ocr": {
      "psm7": "",
      "psm6": "Sa EEE USE tt Nytt Experiment,\n—"
    },
    "chapter": null,
    "page_num": null
  },
  "Biologi-Stella-kapitel-1/006": {
    "ocr": {
      "psm7": ": J = od d - 3 ee 2 ; ace",
      "psm6": "skapliga metoden. =\nnaturvetenskapliga metoden Färm Fa =.\n| | =q ER T."
    },
    "chapter": null,
    "page_num": null
  },
  "Biologi-Stella-kapitel-1/007": {
    "ocr": {
      "psm7": "+ Mo jr)",
      "psm6": "SIV LW WI\nBx"
    },
    "chapter": null,
    "page_num": null
  },
  "Biologi-Stella-kapitel-1/008": {
    "ocr": {
      "psm7": "",
      "psm6": "» Anpassningar i samspel med andra organismer\n»« Ekosystemtjänster Ja"
    },
    "chapter": null,
    "page_num": null
  },
  "Biologi-Stella-kapitel-1/009": {
    "ocr": {
      "psm7": "",
      "psm6": "Pysrsem: w — + & är TAR 4\nför Organismet. a ' pre NG\nP6"
    },
    "chapter": "P",
    "page_num": 6
  },
  "Biologi-Stella-kapitel-1/010": {
    "ocr": {
      "psm7": "EKoLoGI 3& 11",
      "psm6": "EKoLoGI 3& 11\n«"
    },
    "chapter": "EKoLoGI 3&",
    "page_num": 11
  },
  "Biologi-Stella-kapitel-1/011": {
    "ocr": {
      "psm7": "SS",
      "psm6": "SS"
    },
    "chapter": null,
    "page_num": null
  },
  "Biologi-Stella-kapitel-1/012": {
    "ocr": {
      "psm7": "",
      "psm6": "EKOLOGI JK 13"
    },
    "chapter": "EKOLOGI JK",
    "page_num": 13
  },
  "Biologi-Stella-kapitel-1/013": {
    "ocr": {
      "psm7": "ARR => | | 2 5 SN 7 | ” : - ,",
      "psm6": "I a N & 7 a /\n= Al na D > / | - ä. = i -” hu TE"
    },
    "chapter": null,
    "page_num": null
  },
  "Biologi-Stella-kapitel-1/014": {
    "ocr": {
      "psm7": "E dj ; |",
      "psm6": "- t j\nn - £ ) , IIIDEESEeNE EN —\n| td FAN - LÄNS mma\nF SS\n= 3 UK\nPJ MY a\ni ST é\nrr \"FR T\nJIA LJ\nVS 3 al 5\n=! mV\nKN ["
    },
    "chapter": "VS 3 al",
    "page_num": 5
  },
  "Biologi-Stella-kapitel-1/015": {
    "ocr": {
      "psm7": "",
      "psm6": "+F .\nbl\nih 5\n=\" oo d c Fe"
    },
    "chapter": "ih",
    "page_num": 5
  },
  "Biologi-Stella-kapitel-1/016": {
    "ocr": {
      "psm7": "H KS BIE oe",
      "psm6": "| EN | a | ENE en TA RN\nEKoLOG! JK 17\n="
    },
    "chapter": "EKoLOG! JK",
    "page_num": 17
  },
  "Biologi-Stella-kapitel-1/017": {
    "ocr": {
      "psm7": "",
      "psm6": "— 0 UL UCT Kd N Uppsta nya arter, |\na - : L j\n- >\nDD Mor c / L (- ee i - |\n' = |\nsa I ' L ;\n\"i LL N < ” < fn SE Jå\n| - Å (+ i i å 4 F\n” I ee\n—— SR e rn -"
    },
    "chapter": null,
    "page_num": null
  },
  "Biologi-Stella-kapitel-1/018": {
    "ocr": {
      "psm7": "ka a 2 19",
      "psm6": "Lo EKOLOGI JK 19\nFr"
    },
    "chapter": "ka a 2",
    "page_num": 19
  },
  "Biologi-Stella-kapitel-1/019": {
    "ocr": {
      "psm7": "; | e Pe SER z i så SÅ",
      "psm6": "4 ö ) N : EN VY rt om , »d AN Ugk\na ; FE a a + allt 2 ing 1 s"
    },
    "chapter": null,
    "page_num": null
  },
  "Biologi-Stella-kapitel-1/020": {
    "ocr": {
      "psm7": "",
      "psm6": "Te 2 SN I Förl rNN kg EE fö ANG Iaf lr CNE\nor FS SN É ekoroct 3 21\n——— za : ? G /"
    },
    "chapter": "or FS SN É ekoroct 3",
    "page_num": 21
  },
  "Biologi-Stella-kapitel-1/021": {
    "ocr": {
      "psm7": "",
      "psm6": ") ige"
    },
    "chapter": null,
    "page_num": null
  },
  "Biologi-Stella-kapitel-1/022": {
    "ocr": {
      "psm7": "",
      "psm6": "— a €3 sf 4 i än\nPRE\n3 ” SM NM NN - sz - EN ; - Ä\nFn SUVANSACNN a IT AR BIR bo ue\nSAL RRSNR re 1 LES vä EKOLOGI JK 23\nSMS MN SS ere RS SS NA 3, SSE\n! Ina SN N YN PITE = å lat SAR Sr vg SS BÄ Så oc"
    },
    "chapter": "SAL RRSNR re 1 LES vä EKOLOGI JK",
    "page_num": 23
  },
  "Biologi-Stella-kapitel-1/023": {
    "ocr": {
      "psm7": "a Livivatten ” ä TU",
      "psm6": "6 Liv på land\n| 24 > ExoLocI Apr\n— - tä\n0 RE js"
    },
    "chapter": null,
    "page_num": null
  },
  "Biologi-Stella-kapitel-1/024": {
    "ocr": {
      "psm7": "",
      "psm6": "MT RR 2007, NS EN\nBlåstång. Rödsallat.\nEKoLoGI JK 25"
    },
    "chapter": "EKoLoGI JK",
    "page_num": 25
  },
  "Biologi-Stella-kapitel-1/025": {
    "ocr": {
      "psm7": "",
      "psm6": ""
    },
    "chapter": null,
    "page_num": null
  },
  "Biologi-Stella-kapitel-1/026": {
    "ocr": {
      "psm7": "i WE ERRSE yn -",
      "psm6": "VW EKOLOGI J& 27\nPP"
    },
    "chapter": "VW EKOLOGI J&",
    "page_num": 27
  },
  "Biologi-Stella-kapitel-1/027": {
    "ocr": {
      "psm7": ": | mg a fldjur och Nb a pe JU, 253 UISJUICH NOT Dana annat",
      "psm6": "RE Pe JU 2 AR UIGJUICIT NOT Dana annat\ntoffeldjur och amöbor.\n28 JK EKOLOGI"
    },
    "chapter": null,
    "page_num": null
  },
  "Biologi-Stella-kapitel-1/028": {
    "ocr": {
      "psm7": "Aa SSA\" VA EGEN a 3 -",
      "psm6": "NN AE NN\nEKOLOGI! JK 29"
    },
    "chapter": "EKOLOGI! JK",
    "page_num": 29
  },
  "Biologi-Stella-kapitel-1/029": {
    "ocr": {
      "psm7": "fee i | Spindeldjur. I ä",
      "psm6": "gj SINA | Spindeldjur. I\n30 JK EKOLOGI"
    },
    "chapter": null,
    "page_num": null
  },
  "Biologi-Stella-kapitel-1/030": {
    "ocr": {
      "psm7": "",
      "psm6": "7 N ;\nHinnkräftor och hoppkräftor är små kräftdjur\nsom ingår i djurplankton i sjöar och hav.\nExoLoGI ak 31"
    },
    "chapter": "ExoLoGI ak",
    "page_num": 31
  },
  "Biologi-Stella-kapitel-1/031": {
    "ocr": {
      "psm7": "",
      "psm6": "Gälarna hos en fisk sitter Å\nalldeles bakom huvudet\noch täcks oftast av gällock. :\n32 JK EKoLoGI (ll\nNE"
    },
    "chapter": null,
    "page_num": null
  },
  "Biologi-Stella-kapitel-1/032": {
    "ocr": {
      "psm7": "",
      "psm6": "d - SERA SITTA oe -"
    },
    "chapter": null,
    "page_num": null
  },
  "Biologi-Stella-kapitel-1/033": {
    "ocr": {
      "psm7": "| NG näring ur trädet, Mo ENG tak OC NHalntar",
      "psm6": ".” 2-0 OS SBSEAa Uldk UC TNlaälInNlltlarf\n\"\"edbrytningssvampar. näring ur trädet,\n34 3 ExoLoci\n- — Vg"
    },
    "chapter": null,
    "page_num": null
  },
  "Biologi-Stella-kapitel-1/034": {
    "ocr": {
      "psm7": "",
      "psm6": "Marken i tallskogar är ofta torr och täcks av lavar, till exempel renlavar (0 VS MR\nsom på bilden till vänster. Till höger växer en blåslav på en gren.\nEKOLOGI JK 35\n= Mö SR"
    },
    "chapter": "EKOLOGI JK",
    "page_num": 35
  },
  "Biologi-Stella-kapitel-1/035": {
    "ocr": {
      "psm7": "",
      "psm6": "33 när D ; ” EES rv FN N - : js"
    },
    "chapter": null,
    "page_num": null
  },
  "Biologi-Stella-kapitel-1/036": {
    "ocr": {
      "psm7": "sn Jin Ä | p : \"2 å I - : ;",
      "psm6": "4 \"Al KR\nd ny Ls\n. MR our\" >\n| - tra. Oc\n- <a sö SJ\nRA smal fn 2\nMN TT re é FOOL\nJ KAT vh\nE v | apr). STR\nTT: pt of"
    },
    "chapter": "RA smal fn",
    "page_num": 2
  },
  "Biologi-Stella-kapitel-1/037": {
    "ocr": {
      "psm7": "",
      "psm6": "+ fr | ”- GS FR Kb NR CA : MN\nEr Sn Är Te RER NR ds"
    },
    "chapter": null,
    "page_num": null
  },
  "Biologi-Stella-kapitel-1/039": {
    "ocr": {
      "psm7": "",
      "psm6": "Druvsockermolekylen\ninnehåller atomslagen kol (svart),\näl. Å syre (röd) och väte (vit).\n40 34 ekoroci\npo"
    },
    "chapter": null,
    "page_num": null
  },
  "Biologi-Stella-kapitel-1/038": {
    "ocr": {
      "psm7": "",
      "psm6": "- p ES rs mA - FL he ”\n— AE ST IE TRA (\nRå 2 a få 3 -\nsa er SR SR a Cr SE MR\n- 3 PR OR\nNn na de ARE EN RA LE AE NE"
    },
    "chapter": null,
    "page_num": null
  },
  "Biologi-Stella-kapitel-1/040": {
    "ocr": {
      "psm7": "- MN | | G ) | | ; Se ekoLoG! 2 41",
      "psm6": "NN | : SIT | ( | EKOLOGI 3 41"
    },
    "chapter": "- MN | | G ) | | ; Se ekoLoG! 2",
    "page_num": 41
  },
  "Biologi-Stella-kapitel-1/041": {
    "ocr": {
      "psm7": "| 42 AK EKOLOGI är | ET Nk - ) Ho i -",
      "psm6": "| Druvsocker «+ Syre =-—>» Koldioxid + Vatten + — Energi\n| CAH,0, 0, CO, H,O\n42 3 EKOLOGI |"
    },
    "chapter": null,
    "page_num": null
  },
  "Biologi-Stella-kapitel-1/042": {
    "ocr": {
      "psm7": "= | ; ; 3 | | kotoar 3 43",
      "psm6": "fo 4 NN | a ;\n= ;\n| ="
    },
    "chapter": "= | ; ; 3 | | kotoar 3",
    "page_num": 43
  },
  "Biologi-Stella-kapitel-1/043": {
    "ocr": {
      "psm7": "",
      "psm6": "som de ser ut i em un 9553, — Iväxternas blad finns många små\n; som de ser ut i ett mikroskop, hål som kallas klyvöppningar.\n44 3 EKOLOGI"
    },
    "chapter": null,
    "page_num": null
  },
  "Biologi-Stella-kapitel-1/044": {
    "ocr": {
      "psm7": "",
      "psm6": "AVE GILA SIR SYRRA RANGEN ANAR Vers Rn nn mA RR nn RR mn nn na di\n| vatten utan också många andra ämnen, bland annat kväve och fosfor.\nEKOLOGI JK 45"
    },
    "chapter": "EKOLOGI JK",
    "page_num": 45
  },
  "Biologi-Stella-kapitel-1/045": {
    "ocr": {
      "psm7": "",
      "psm6": "0 Ope et Berta I SIH Ccellananing\nhela tiden avger koldioxid som kommer ut i atmosfären.\n46 3 EKoroc!\n| -"
    },
    "chapter": null,
    "page_num": null
  },
  "Biologi-Stella-kapitel-1/046": {
    "ocr": {
      "psm7": "",
      "psm6": "/ 4 bn EKxoLOG! 3 47\nCE V |"
    },
    "chapter": "/ 4 bn EKxoLOG! 3",
    "page_num": 47
  },
  "Biologi-Stella-kapitel-1/048": {
    "ocr": {
      "psm7": "",
      "psm6": "PAP SONET SN IS ” « C\nfrån björkbladen som sparvhöken får i sig. RE > SE. JE RE SEG\nEKOLOGI! J€ 49\nmm."
    },
    "chapter": "EKOLOGI! J€",
    "page_num": 49
  },
  "Biologi-Stella-kapitel-1/047": {
    "ocr": {
      "psm7": "",
      "psm6": "” SN K FADERN CS ' KR\nC he. schön"
    },
    "chapter": null,
    "page_num": null
  },
  "Biologi-Stella-kapitel-1/050": {
    "ocr": {
      "psm7": "som är ämnen som alla organismer behöver till sina celler.",
      "psm6": "som är ämnen som alla organismer behöver till sina celler.\nEKOLOGI JK 51\n= oo"
    },
    "chapter": "EKOLOGI JK",
    "page_num": 51
  },
  "Biologi-Stella-kapitel-1/049": {
    "ocr": {
      "psm7": "| 0 den totala vikten av ala organismer i näringskedjorna i en lövskog. 1",
      "psm6": "den Otala ET OJ AEOMIAN pa Hasta Sida ar tankt att ScS som\ntotala vi EN FC SR DERE\nvikten av alla organismer i näringskedjorna i en lövskog.\n50 3 ExoLoci\nE0 |"
    },
    "chapter": "| 0 den totala vikten av ala organismer i näringskedjorna i en lövskog.",
    "page_num": 1
  },
  "Biologi-Stella-kapitel-1/051": {
    "ocr": {
      "psm7": "",
      "psm6": "SS CO VA Jalla MIUI UMHKA arter av |\n| svampar och bakterier men också smådjur som maskar, kvalster, |\n52 3 EKOLOGI\nEE ,\nam mm - -"
    },
    "chapter": null,
    "page_num": null
  },
  "Biologi-Stella-kapitel-1/052": {
    "ocr": {
      "psm7": "| 3 No 5 ; E er é : É U OM s Sa A | EKOLOGI! JK 53 |",
      "psm6": "SS IMSE je AVR I !\n, N -? Så ,\n<q BTR Nyast Le - 3 S =? Ve ”\nMY Ny FRA Ra - NE EKOLOGI JK 53\nVi a é FO E-A Z FK Ven SC 3L\nFR NN nr SN N Fi mys R YT N y /; ,"
    },
    "chapter": "MY Ny FRA Ra - NE EKOLOGI JK",
    "page_num": 53
  },
  "Biologi-Stella-kapitel-1/053": {
    "ocr": {
      "psm7": "+ TN",
      "psm6": "+ TN"
    },
    "chapter": null,
    "page_num": null
  },
  "Biologi-Stella-kapitel-1/054": {
    "ocr": {
      "psm7": "VV NVaYvE SOIT) BS I IUTTCIL. -",
      "psm6": "VV NVaYvE SOIT) BS I IUTTCIL.\noo 2\nso EE RNE"
    },
    "chapter": "oo",
    "page_num": 2
  },
  "Biologi-Stella-kapitel-1/055": {
    "ocr": {
      "psm7": "",
      "psm6": "TE = Häls sa frå ns\n- RR veck Å 3 1\n) PFRÖLDG = Ner | a\n1 I\n| ul FA N\nTi oc MN TN å ”"
    },
    "chapter": "- RR veck Å 3",
    "page_num": 1
  },
  "Biologi-Stella-kapitel-1/056": {
    "ocr": {
      "psm7": "",
      "psm6": "| å Tr £ frå pu Fn\nIV ä / K I Gr Sot c - i EKOLOGEE-NE: RR\n| JE - ES NESS sär år | FN\nH | Å \"a z -\n| - Se = TER Mä"
    },
    "chapter": null,
    "page_num": null
  },
  "Biologi-Stella-kapitel-1/057": {
    "ocr": {
      "psm7": "",
      "psm6": "SSA nn\nBö NRA SES (SKE |\nSN | Bor CN v Ja od kara NE AS \"Rs En I\nTR Ye Fö EAS\na NET AR"
    },
    "chapter": null,
    "page_num": null
  },
  "Biologi-Stella-kapitel-1/059": {
    "ocr": {
      "psm7": "",
      "psm6": "| |\nI"
    },
    "chapter": null,
    "page_num": null
  },
  "Biologi-Stella-kapitel-1/058": {
    "ocr": {
      "psm7": "",
      "psm6": "> Trästicka FR REN åa Ag 0 cs ra Se\nNN Å VR Eg - RN RTR EYE ns n\nRR ag SN NR KS EA\nbh -: SS 47 EE raden TE\n7 NRA NR KESR ” NI Ur ;\n1 X H SR ÄT = \"ang FRA AR ERE of\n- HN Va CO FRU - ( , é -"
    },
    "chapter": null,
    "page_num": null
  },
  "Biologi-Stella-kapitel-1/060": {
    "ocr": {
      "psm7": "",
      "psm6": "vIDöH BICKSI VRT FSE UDI Of I -\nlever på marken och jagar utan nät. FÖRS Ae rr En\nExoroG! 3 61"
    },
    "chapter": "ExoroG! 3",
    "page_num": 61
  },
  "Biologi-Stella-kapitel-1/061": {
    "ocr": {
      "psm7": "",
      "psm6": "RE Se et ett DIC Ul Sina Dlad ordentlugt och skugga\nde andra växterna som då blir små och svaga och kanske dör.\n62 3 EkorocI\n—L"
    },
    "chapter": null,
    "page_num": null
  },
  "Biologi-Stella-kapitel-1/062": {
    "ocr": {
      "psm7": "",
      "psm6": "I d |\nKardborre Blåbär finssel\nEKOLOGI & 63"
    },
    "chapter": "EKOLOGI &",
    "page_num": 63
  },
  "Biologi-Stella-kapitel-1/063": {
    "ocr": {
      "psm7": "64 3 EKxoLoGi vä | | ; sq :",
      "psm6": "| od JAG\n| 64 3 EKoLocI : i"
    },
    "chapter": null,
    "page_num": null
  },
  "Biologi-Stella-kapitel-1/064": {
    "ocr": {
      "psm7": "",
      "psm6": "— pr SE,\nSvampen tar upp vatten och närsalter 4-4 EEE EE EIN\nsom transporteras upp till växten.\nRR"
    },
    "chapter": null,
    "page_num": null
  },
  "Biologi-Stella-kapitel-1/065": {
    "ocr": {
      "psm7": "",
      "psm6": "uu = NES\n- a '\nI\n' I\n1\ntt i"
    },
    "chapter": null,
    "page_num": 1
  },
  "Biologi-Stella-kapitel-1/066": {
    "ocr": {
      "psm7": "| ee mm 22 H",
      "psm6": "| EKOLOGI! JK 67\n7 a"
    },
    "chapter": "| EKOLOGI! JK",
    "page_num": 67
  },
  "Biologi-Stella-kapitel-1/067": {
    "ocr": {
      "psm7": "",
      "psm6": "- LJ\n- |\nLE -\nUl"
    },
    "chapter": null,
    "page_num": null
  },
  "Biologi-Stella-kapitel-1/068": {
    "ocr": {
      "psm7": "",
      "psm6": "EKOLOGI JK GI"
    },
    "chapter": null,
    "page_num": null
  },
  "Biologi-Stella-kapitel-1/069": {
    "ocr": {
      "psm7": "| 4 . ; larterer BRG de få ädipa SS en näringskedja nar man",
      "psm6": "FAUURCIH Halulat OM vad Som > € \"då\nplanterar fftämmande träd i äker.i en näringskedja nar man\n70 3 EKxoLoGI"
    },
    "chapter": null,
    "page_num": null
  },
  "Biologi-Stella-kapitel-1/070": {
    "ocr": {
      "psm7": "| ; Källhänvisningar. Resonera kring artikeln med två av dessa , n j",
      "psm6": "Källhänvisningar. Resonera kring artikeln med två av dessa källkritiska perspektiv. | |\nEkoLoGI 3 71"
    },
    "chapter": "EkoLoGI 3",
    "page_num": 71
  },
  "Biologi-Stella-kapitel-1/071": {
    "ocr": {
      "psm7": "| 72 AK EKOLOGI ö pA ; fy i |",
      "psm6": "$ j\n72 3 EKOLOGI ö 2 fj\nt ola / ; |"
    },
    "chapter": null,
    "page_num": null
  },
  "Biologi-Stella-kapitel-1/072": {
    "ocr": {
      "psm7": "3 SÅR N 7 | | EKOLOGI 2 73",
      "psm6": "QR ? =\nFINNS AN\nSN PRI\n2 på SN A EKOLOGI J& 73\n. NYN . | -\nSE Le ON Nn RE"
    },
    "chapter": "3 SÅR N 7 | | EKOLOGI 2",
    "page_num": 73
  },
  "Biologi-Stella-kapitel-1/073": {
    "ocr": {
      "psm7": "",
      "psm6": "nä 2 kl TREE i\n> FR I 3 a al d\n\nLU V a > SA '\n\n| + I 0 -! ” AA N\n\nfa ARA ae x vw Sd HL - a.\n\n: Å I Kock 3"
    },
    "chapter": ": Å I Kock",
    "page_num": 3
  },
  "Biologi-Stella-kapitel-1/074": {
    "ocr": {
      "psm7": "",
      "psm6": "s = > |\nMH - EKOLOGI! vr JIny\nFJ lä NE EW\n<\n\" en\nÉ '"
    },
    "chapter": null,
    "page_num": null
  },
  "Biologi-Stella-kapitel-1/075": {
    "ocr": {
      "psm7": "\"—-— ar naturliga fiender till arter som är skadegörare I skogen.",
      "psm6": "R ar naturliga fiender till arter som är skadegörare I skogen.\n|\n76 3 EKOLOGI"
    },
    "chapter": null,
    "page_num": null
  },
  "Biologi-Stella-kapitel-1/076": {
    "ocr": {
      "psm7": "",
      "psm6": "(å ÖN 6 MITT. ee ee VIN\nÅ I nov - Tag + | -\nPl så rea oc . EKOLO Mr\nI IHY of i: I rå IS"
    },
    "chapter": null,
    "page_num": null
  }
}